publiscord/__init__.py
publiscord/main.py
publiscord-0.0.1.dist-info/LICENSE
publiscord-0.0.1.dist-info/METADATA
publiscord-0.0.1.dist-info/WHEEL
publiscord-0.0.1.dist-info/top_level.txt
publiscord-0.0.1.dist-info/RECORD
